izmacalculator/__init__.py
izmacalculator/main.py
izmacalculator-0.1.dist-info/LICENSE.txt
izmacalculator-0.1.dist-info/METADATA
izmacalculator-0.1.dist-info/WHEEL
izmacalculator-0.1.dist-info/entry_points.txt
izmacalculator-0.1.dist-info/top_level.txt
izmacalculator-0.1.dist-info/RECORD
