Metadata-Version: 2.1
Name: izmacalculator
Version: 0.1
Summary: This package provides basic calculator functionalities
Author: Izma Daudiya
Author-email: daudiyaizma@gmail.com
License: MIT
Classifier: Programming Language :: Python :: 3
Classifier: License :: OSI Approved :: MIT License
Classifier: Operating System :: OS Independent
Requires-Python: >=3.10
License-File: LICENSE.txt
Provides-Extra: dev
Requires-Dist: pytest>=7.0; extra == "dev"
Requires-Dist: twine>=4.0.2; extra == "dev"
